poetry_experiment/__init__.py
poetry_experiment/__main__.py
poetry_experiment/program.py
poetry_experiment-0.1.1.dist-info/METADATA
poetry_experiment-0.1.1.dist-info/WHEEL
poetry_experiment-0.1.1.dist-info/entry_points.txt
poetry_experiment-0.1.1.dist-info/RECORD
