Metadata-Version: 2.1
Name: poetry-experiment
Version: 0.1.1
Summary: Testing poetry, Correct Python Packaging, installing and running as cli
Author: Tami Bar
Author-email: fire17@gmail.com
Requires-Python: >=3,<4
Classifier: Programming Language :: Python :: 3
Classifier: Programming Language :: Python :: 3.4
Classifier: Programming Language :: Python :: 3.5
Classifier: Programming Language :: Python :: 3.6
Classifier: Programming Language :: Python :: 3.7
Classifier: Programming Language :: Python :: 3.8
Classifier: Programming Language :: Python :: 3.9
Classifier: Programming Language :: Python :: 3.10
Classifier: Programming Language :: Python :: 3.11
Classifier: Programming Language :: Python :: 3.12
